geo_inference/__init__.py
geo_inference/geo_dask.py
geo_inference/geo_inference.py
geo_inference/config/__init__.py
geo_inference/config/log_config.yaml
geo_inference/config/logging_config.py
geo_inference/config/sample.yaml
geo_inference/utils/__init__.py
geo_inference/utils/geo.py
geo_inference/utils/geo_transforms.py
geo_inference/utils/helpers.py
geo_inference/utils/polygon.py
geo_inference-3.2.4.dist-info/licenses/LICENSE
geo_inference-3.2.4.dist-info/METADATA
geo_inference-3.2.4.dist-info/WHEEL
geo_inference-3.2.4.dist-info/entry_points.txt
geo_inference-3.2.4.dist-info/top_level.txt
geo_inference-3.2.4.dist-info/RECORD
