Metadata-Version: 2.4
Name: geo-inference
Version: 3.2.4
Summary: Extract features from geospatial imagery using deep learning models
Author-email: Victor Alhassan <victor.alhassan@nrcan-rncan.gc.ca>
Project-URL: Homepage, https://github.com/NRCan/geo-inference
Keywords: pytorch,deep learning,machine learning,remote sensing,satellite imagery,earth observation,geospatial
Classifier: Development Status :: 3 - Alpha
Classifier: Intended Audience :: Science/Research
Classifier: License :: OSI Approved :: MIT License
Classifier: Programming Language :: Python :: 3.11
Classifier: Topic :: Scientific/Engineering :: Artificial Intelligence
Classifier: Topic :: Scientific/Engineering :: GIS
Requires-Python: >=3.9
License-File: LICENSE
Requires-Dist: torchgeo>=0.5.2
Requires-Dist: affine>=2.4.0
Requires-Dist: colorlog==6.7.0
Requires-Dist: scipy>=1.13.1
Requires-Dist: pyyaml>=5.2
Requires-Dist: nvidia-ml-py>=11.4
Requires-Dist: geopandas>=0.14.4
Requires-Dist: dask-image>=2024.5.3
Requires-Dist: dask[distributed]>=2024.6.2
Requires-Dist: requests>=2.32.3
Requires-Dist: xarray>=2024.6.0
Requires-Dist: pystac>=1.10.1
Requires-Dist: rioxarray>=0.15.6
Requires-Dist: ttach>=0.0.3
Requires-Dist: rtree>=1.0
Provides-Extra: dev
Requires-Dist: black; extra == "dev"
Requires-Dist: bumpver; extra == "dev"
Requires-Dist: isort; extra == "dev"
Requires-Dist: pip-tools; extra == "dev"
Requires-Dist: pytest; extra == "dev"
Dynamic: license-file
